agents/__init__.py
agents/model.py
agents/tester.py
agents/ui.py
AgentsPy-0.8.1.dist-info/LICENSE
AgentsPy-0.8.1.dist-info/METADATA
AgentsPy-0.8.1.dist-info/WHEEL
AgentsPy-0.8.1.dist-info/top_level.txt
AgentsPy-0.8.1.dist-info/RECORD
