Metadata-Version: 2.1
Name: AgentsPy
Version: 0.8.1
Summary: Simple agent-based modeling library for python
Home-page: https://github.com/DatalogiForAlle/pyagents
Author: Jens Kanstrup Larsen / Martin Dybdal
Author-email: jkl@di.ku.dk
License: gpl-3.0
Download-URL: https://github.com/DatalogiForAlle/AgentsPy/releases/tag/v0.1
Keywords: AGENT,MODELING,SIMULATION
Platform: UNKNOWN
Classifier: Development Status :: 4 - Beta
Classifier: Intended Audience :: Developers
Classifier: Topic :: Software Development :: Build Tools
Classifier: License :: OSI Approved :: GNU General Public License v3 (GPLv3)
Classifier: Programming Language :: Python :: 3
Classifier: Programming Language :: Python :: 3.4
Classifier: Programming Language :: Python :: 3.5
Classifier: Programming Language :: Python :: 3.6
Requires-Dist: PyQt5
Requires-Dist: PyQtChart
Provides-Extra: dev
Requires-Dist: black ; extra == 'dev'
Requires-Dist: sphinx ; extra == 'dev'
Requires-Dist: alabaster ; extra == 'dev'
Provides-Extra: docs
Requires-Dist: sphinx ; extra == 'docs'
Requires-Dist: alabaster ; extra == 'docs'
Provides-Extra: tests
Requires-Dist: black ; extra == 'tests'
